omniqubo/__init__.py
omniqubo/constants.py
omniqubo/constraints.py
omniqubo/model.py
omniqubo/omniqubo.py
omniqubo/transpiler.py
omniqubo/vars.py
omniqubo/converters/__init__.py
omniqubo/converters/converter.py
omniqubo/converters/eq_to_objective.py
omniqubo/converters/ineq_to_eq.py
omniqubo/converters/quadratize.py
omniqubo/converters/simple_manipulation.py
omniqubo/converters/utils.py
omniqubo/converters/varreplace.py
omniqubo/models/__init__.py
omniqubo/models/sympyopt/__init__.py
omniqubo/models/sympyopt/constraints.py
omniqubo/models/sympyopt/converters.py
omniqubo/models/sympyopt/sympyopt.py
omniqubo/models/sympyopt/utils.py
omniqubo/models/sympyopt/vars.py
omniqubo/models/sympyopt/transpiler/__init__.py
omniqubo/models/sympyopt/transpiler/dimod_to_sympyopt.py
omniqubo/models/sympyopt/transpiler/docplex_to_sympyopt.py
omniqubo/models/sympyopt/transpiler/pulp_to_sympyopt.py
omniqubo/models/sympyopt/transpiler/qiskit_to_sympyopt.py
omniqubo/models/sympyopt/transpiler/sympyopt_to_dimod.py
omniqubo/models/sympyopt/transpiler/sympyopt_to_qiskit.py
omniqubo/models/sympyopt/transpiler/transpiler.py
omniqubo/sampleset/__init__.py
omniqubo/sampleset/_dimod_import.py
omniqubo/utils/__init__.py
omniqubo/utils/utils.py
omniqubo-0.1.0.dist-info/LICENSE
omniqubo-0.1.0.dist-info/METADATA
omniqubo-0.1.0.dist-info/WHEEL
omniqubo-0.1.0.dist-info/top_level.txt
omniqubo-0.1.0.dist-info/RECORD
